[
    {
        "id": 1,
        "nombre": "The Legend of Zelda: Breath of the Wild",
        "descripcion": "Un juego de acción y aventuras en un mundo abierto donde los jugadores pueden explorar el reino de Hyrule.",
        "precio": 59.99,
        "stock": 20,
        "categoria": "Aventura"
    },
    {
        "id": 2,
        "nombre": "Super Mario Odyssey",
        "descripcion": "Un juego de plataformas en 3D donde Mario viaja a través de diversos mundos para rescatar a la Princesa Peach de Bowser.",
        "precio": 49.99,
        "stock": 15,
        "categoria": "Plataformas"
    },
    {
        "id": 3,
        "nombre": "Animal Crossing: New Horizons",
        "descripcion": "Un juego de simulación de vida donde los jugadores pueden crear su propia isla paradisíaca.",
        "precio": 59.99,
        "stock": 25,
        "categoria": "Simulación"
    },
    {
        "id": 4,
        "nombre": "Splatoon 2",
        "descripcion": "Un juego de disparos en tercera persona donde los jugadores controlan a los Inklings y compiten en batallas de pintura.",
        "precio": 39.99,
        "stock": 30,
        "categoria": "Acción"
    },
    {
        "id": 5,
        "nombre": "Mario Kart 8 Deluxe",
        "descripcion": "Un juego de carreras con personajes del universo de Mario, que incluye modos multijugador tanto en línea como local.",
        "precio": 59.99,
        "stock": 10,
        "categoria": "Carreras"
    },
    {
        "id": 6,
        "nombre": "Minecraft",
        "descripcion": "Un juego de construcción y supervivencia donde los jugadores pueden explorar, construir y sobrevivir en un mundo generado por procedimientos.",
        "precio": 29.99,
        "stock": 50,
        "categoria": "Aventura"
    },
    {
        "id": 7,
        "nombre": "Fortnite",
        "descripcion": "Un juego de batalla real y construcción donde los jugadores compiten para ser el último en pie.",
        "precio": 0.00,
        "stock": 100,
        "categoria": "Acción"
    },
    {
        "id": 8,
        "nombre": "Pokémon Sword",
        "descripcion": "Un juego de rol donde los jugadores capturan y entrenan Pokémon para convertirse en el campeón de la región de Galar.",
        "precio": 59.99,
        "stock": 20,
        "categoria": "Rol"
    },
    {
        "id": 9,
        "nombre": "The Witcher 3: Wild Hunt",
        "descripcion": "Un juego de rol y acción en un mundo abierto donde los jugadores asumen el papel de Geralt de Rivia, un cazador de monstruos.",
        "precio": 39.99,
        "stock": 15,
        "categoria": "Rol"
    },
    {
        "id": 10,
        "nombre": "Cyberpunk 2077",
        "descripcion": "Un juego de rol y acción en un futuro distópico, con un mundo abierto y una narrativa inmersiva.",
        "precio": 59.99,
        "stock": 5,
        "categoria": "Acción"
    }
]